oze_canopen-0.1.0.dist-info/METADATA
oze_canopen-0.1.0.dist-info/WHEEL
oze_canopen.libs/libgcc_s-5b5488a6.so.1
oze_canopen/__init__.py
oze_canopen/oze_canopen.cpython-313t-arm-linux-musleabihf.so
oze_canopen-0.1.0.dist-info/RECORD
