Metadata-Version: 2.4
Name: oze-canopen
Version: 0.1.0
Classifier: Programming Language :: Rust
Classifier: Programming Language :: Python :: Implementation :: CPython
Classifier: Programming Language :: Python :: Implementation :: PyPy
Summary: OZON CANOpen library Python bindings
Home-Page: https://github.com/ozontech/oze-canopen
Author: OZON TECH, Aleksandr Lutsai <s.lyra@ya.ru>
Author-email: OZON TECH, Aleksandr Lutsai <s.lyra@ya.ru>
License: Apache-2.0
Requires-Python: >=3.8
Project-URL: Source Code, https://github.com/ozontech/oze-canopen
